How2jJavaZhongjiJiaocheng/README.md
How2jJavaZhongjiJiaocheng/__init__.py
How2jJavaZhongjiJiaocheng/__main__.py
How2jJavaZhongjiJiaocheng/file.epub
How2jJavaZhongjiJiaocheng/index.html
How2jJavaZhongjiJiaocheng/css/__init__.py
How2jJavaZhongjiJiaocheng/css/annotations.css
How2jJavaZhongjiJiaocheng/css/main.css
How2jJavaZhongjiJiaocheng/css/normalize.css
How2jJavaZhongjiJiaocheng/css/popup.css
How2jJavaZhongjiJiaocheng/font/__init__.py
How2jJavaZhongjiJiaocheng/font/fontello.eot
How2jJavaZhongjiJiaocheng/font/fontello.svg
How2jJavaZhongjiJiaocheng/font/fontello.ttf
How2jJavaZhongjiJiaocheng/font/fontello.woff
How2jJavaZhongjiJiaocheng/img/__init__.py
How2jJavaZhongjiJiaocheng/img/annotator-glyph-sprite.png
How2jJavaZhongjiJiaocheng/img/annotator-icon-sprite.png
How2jJavaZhongjiJiaocheng/img/apple-touch-icon.png
How2jJavaZhongjiJiaocheng/img/cancelfullscreen.png
How2jJavaZhongjiJiaocheng/img/close.png
How2jJavaZhongjiJiaocheng/img/fullscreen.png
How2jJavaZhongjiJiaocheng/img/loader.gif
How2jJavaZhongjiJiaocheng/img/menu-icon.png
How2jJavaZhongjiJiaocheng/img/save.png
How2jJavaZhongjiJiaocheng/img/saved.png
How2jJavaZhongjiJiaocheng/img/settings-s.png
How2jJavaZhongjiJiaocheng/img/settings.png
How2jJavaZhongjiJiaocheng/img/star.png
How2jJavaZhongjiJiaocheng/js/__init__.py
How2jJavaZhongjiJiaocheng/js/epub.js
How2jJavaZhongjiJiaocheng/js/epub.min.js
How2jJavaZhongjiJiaocheng/js/epub.min.map
How2jJavaZhongjiJiaocheng/js/hooks.min.js
How2jJavaZhongjiJiaocheng/js/hooks.min.map
How2jJavaZhongjiJiaocheng/js/reader.js
How2jJavaZhongjiJiaocheng/js/reader.js.map
How2jJavaZhongjiJiaocheng/js/reader.min.js
How2jJavaZhongjiJiaocheng/js/reader.min.map
How2jJavaZhongjiJiaocheng/js/hooks/__init__.py
How2jJavaZhongjiJiaocheng/js/hooks/extensions/__init__.py
How2jJavaZhongjiJiaocheng/js/hooks/extensions/highlight.js
How2jJavaZhongjiJiaocheng/js/libs/__init__.py
How2jJavaZhongjiJiaocheng/js/libs/jquery.min.js
How2jJavaZhongjiJiaocheng/js/libs/localforage.min.js
how2j_java_zhongji_jiaocheng-2024.3.5.0.dist-info/METADATA
how2j_java_zhongji_jiaocheng-2024.3.5.0.dist-info/WHEEL
how2j_java_zhongji_jiaocheng-2024.3.5.0.dist-info/entry_points.txt
how2j_java_zhongji_jiaocheng-2024.3.5.0.dist-info/top_level.txt
how2j_java_zhongji_jiaocheng-2024.3.5.0.dist-info/RECORD
